hiplot/__init__.py
hiplot/__main__.py
hiplot/compress.py
hiplot/experiment.py
hiplot/fetchers.py
hiplot/fetchers_demo.py
hiplot/ipython.py
hiplot/pkginfo.py
hiplot/py.typed
hiplot/render.py
hiplot/server.py
hiplot/streamlit_helpers.py
hiplot/test_experiment.py
hiplot/test_fetchers.py
hiplot/test_render.py
hiplot/static/icon-w.svg
hiplot/static/icon.png
hiplot/static/icon.svg
hiplot/static/logo-w.svg
hiplot/static/logo.png
hiplot/static/logo.svg
hiplot/static/thumbnail.png
hiplot/static/built/component.d.ts
hiplot/static/built/component.js
hiplot/static/built/contextmenu.d.ts
hiplot/static/built/contextmenu.js
hiplot/static/built/controls.d.ts
hiplot/static/built/controls.js
hiplot/static/built/filters.d.ts
hiplot/static/built/filters.js
hiplot/static/built/header.d.ts
hiplot/static/built/header.js
hiplot/static/built/hiplot-mm-0.0.0.tar.gz
hiplot/static/built/hiplot.bundle.js
hiplot/static/built/hiplot.bundle.js.LICENSE.txt
hiplot/static/built/hiplot.bundle.js.map
hiplot/static/built/hiplot.d.ts
hiplot/static/built/hiplot.js
hiplot/static/built/hiplot.lib.js
hiplot/static/built/hiplot.lib.js.map
hiplot/static/built/hiplot.licenses.txt
hiplot/static/built/hiplot_mm-0.0.0-py3-none-any.whl
hiplot/static/built/hiplot_streamlit.bundle.js
hiplot/static/built/hiplot_streamlit.bundle.js.LICENSE.txt
hiplot/static/built/hiplot_streamlit.bundle.js.map
hiplot/static/built/hiplot_streamlit.d.ts
hiplot/static/built/hiplot_streamlit.js
hiplot/static/built/hiplot_streamlit.licenses.txt
hiplot/static/built/hiplot_test.bundle.js
hiplot/static/built/hiplot_test.bundle.js.LICENSE.txt
hiplot/static/built/hiplot_test.bundle.js.map
hiplot/static/built/hiplot_test.d.ts
hiplot/static/built/hiplot_test.js
hiplot/static/built/hiplot_test.licenses.txt
hiplot/static/built/hiplot_web.d.ts
hiplot/static/built/hiplot_web.js
hiplot/static/built/infertypes.d.ts
hiplot/static/built/infertypes.js
hiplot/static/built/plotxy.d.ts
hiplot/static/built/plotxy.js
hiplot/static/built/plugin.d.ts
hiplot_mm-0.0.2.dist-info/LICENSE
hiplot_mm-0.0.2.dist-info/METADATA
hiplot_mm-0.0.2.dist-info/NOTICE
hiplot_mm-0.0.2.dist-info/WHEEL
hiplot_mm-0.0.2.dist-info/entry_points.txt
hiplot_mm-0.0.2.dist-info/top_level.txt
hiplot_mm-0.0.2.dist-info/RECORD
