Metadata-Version: 2.1
Name: hiplot-mm
Version: 0.0.2
Summary: High dimensional Interactive Plotting tool
Home-page: https://github.com/facebookresearch/hiplot
Author: Facebook AI Research
License: UNKNOWN
Platform: UNKNOWN
Requires-Python: >=3.6
License-File: LICENSE
License-File: NOTICE
Requires-Dist: ipython >=7.0.1
Requires-Dist: flask
Requires-Dist: flask-compress
Requires-Dist: beautifulsoup4
Provides-Extra: dev
Requires-Dist: pytest ; extra == 'dev'
Requires-Dist: mypy ; extra == 'dev'
Requires-Dist: ipykernel ; extra == 'dev'
Requires-Dist: wheel ; extra == 'dev'
Requires-Dist: selenium ; extra == 'dev'
Requires-Dist: mistune ==0.8.4 ; extra == 'dev'
Requires-Dist: twine ; extra == 'dev'
Requires-Dist: pre-commit ; extra == 'dev'
Requires-Dist: pandas ; extra == 'dev'
Requires-Dist: streamlit >=0.63 ; extra == 'dev'
Requires-Dist: beautifulsoup4 ; extra == 'dev'
Requires-Dist: optuna ; extra == 'dev'
Requires-Dist: sphinx ==5.2.0 ; extra == 'dev'
Requires-Dist: guzzle-sphinx-theme ==0.7.11 ; extra == 'dev'
Requires-Dist: m2r2 ==0.3.3 ; extra == 'dev'
